influx_logging/__init__.py
influx_logging/handler.py
influx_logging-0.2.0.dist-info/DESCRIPTION.rst
influx_logging-0.2.0.dist-info/METADATA
influx_logging-0.2.0.dist-info/RECORD
influx_logging-0.2.0.dist-info/WHEEL
influx_logging-0.2.0.dist-info/metadata.json
influx_logging-0.2.0.dist-info/top_level.txt
tests/test_influx_handler.py
