Metadata-Version: 2.0
Name: influx-logging
Version: 0.2.0
Summary: Handlers for using InfluxDB as your logging backend.
Home-page: https://github.com/teamworksapp/influx_logging
Author: Jefferson Heard
Author-email: jheard@teamworks.com
License: MIT
Platform: UNKNOWN
Classifier: Programming Language :: Python :: 3
Classifier: Development Status :: 3 - Alpha
Classifier: Topic :: Software Development :: Build Tools
Classifier: Topic :: System :: Logging
Requires-Python: >=3
Requires-Dist: influxdb
